LICENSE
README.md
README.rst
setup.py
ezeth/__init__.py
ezeth/base.py
ezeth/exception.py
ezeth/utils.py
ezeth/version.py
ezeth.egg-info/PKG-INFO
ezeth.egg-info/SOURCES.txt
ezeth.egg-info/dependency_links.txt
ezeth.egg-info/requires.txt
ezeth.egg-info/top_level.txt