Metadata-Version: 2.1
Name: ezeth
Version: 1.1.0.post1
Summary: simple python client to access ethereum network
Home-page: https://github.com/fahadh4ilyas/Simple-Ethereum-Client.git
Author: Ahmad Fahadh Ilyas
Author-email: fahadhilyas4@gmail.com
License: MIT
Keywords: ethereum,web3,solidity
Platform: UNKNOWN
Classifier: Development Status :: 5 - Production/Stable
Classifier: Programming Language :: Python :: 3 :: Only
Classifier: License :: OSI Approved :: MIT License
Classifier: Topic :: Utilities
Requires-Python: >=3.7,<3.11
License-File: LICENSE
